cep_scraper/__init__.py
cep_scraper/client.py
tests/__init__.py
tests/test_cep.py
cep_scraper-0.0.5.dist-info/LICENSE
cep_scraper-0.0.5.dist-info/METADATA
cep_scraper-0.0.5.dist-info/WHEEL
cep_scraper-0.0.5.dist-info/top_level.txt
cep_scraper-0.0.5.dist-info/RECORD
