Metadata-Version: 2.1
Name: cep-scraper
Version: 0.0.5
Summary: Consult transactions in CEP.
Home-page: https://github.com/cuenca-mx/cep-scraper
Author: Cuenca
Author-email: dev@cuenca.com
License: UNKNOWN
Platform: UNKNOWN
Classifier: Programming Language :: Python :: 3
Classifier: License :: OSI Approved :: MIT License
Classifier: Operating System :: OS Independent
Requires-Dist: requests (<2.22.0,>=2.21.0)
Provides-Extra: test
Requires-Dist: pytest ; extra == 'test'
Requires-Dist: pytest-vcr ; extra == 'test'
Requires-Dist: pycodestyle ; extra == 'test'
Requires-Dist: pytest-cov ; extra == 'test'
Requires-Dist: black ; extra == 'test'
Requires-Dist: isort ; extra == 'test'
